{"type": "FeatureCollection", "features": [{"type": "Feature", "geometry": {"type": "Point", "coordinates": [-113.4695, 53.5198]}, "properties": {"Lot Name": "Lot at 9515 Carson Bend", "Address": "9515 Carson Bend, Edmonton, AB", "Builder": "Prominent Homes", "Status": "Available", "Community": "Chapelle"}}, {"type": "Feature", "geometry": {"type": "Point", "coordinates": [-113.469, 53.5196]}, "properties": {"Lot Name": "Lot at 9538 Carson Bend", "Address": "9538 Carson Bend, Edmonton, AB", "Builder": "Prominent Homes", "Status": "Available", "Community": "Chapelle"}}, {"type": "Feature", "geometry": {"type": "Point", "coordinates": [-113.4689, 53.5195]}, "properties": {"Lot Name": "Lot at 9540 Carson Bend", "Address": "9540 Carson Bend, Edmonton, AB", "Builder": "Prominent Homes", "Status": "Available", "Community": "Chapelle"}}]}